<!-- Indices written at Fri, 16 Nov 2012 20:02:48 GMT+05:30 -->

<datastore-indexes>

    <!-- Used 8 times in query history -->
    <datastore-index kind="ConfessionDO" ancestor="false" source="auto">
        <property name="isVisibleOnPublicWall" direction="asc"/>
        <property name="timeStamp" direction="desc"/>
    </datastore-index>

    <!-- Used 52 times in query history -->
    <datastore-index kind="PardonConditionDO" ancestor="true" source="auto">
        <property name="pardonConditionDOs_INTEGER_IDX" direction="asc"/>
    </datastore-index>

    <!-- Used 8 times in query history -->
    <datastore-index kind="ConfessionDO" ancestor="false" source="auto">
        <property name="userId" direction="asc"/>
        <property name="timeStamp" direction="desc"/>
    </datastore-index>

    <!-- Used 2 times in query history -->
    <datastore-index kind="ConfessionShareDO" ancestor="false" source="auto">
        <property name="userId" direction="asc"/>
        <property name="timeStamp" direction="desc"/>
    </datastore-index>

</datastore-indexes>
